pandas_decimal/__init__.py
pandas_decimal/array.py
pandas_decimal/dtype.py
pandas_decimal-0.0.1.dist-info/LICENSE
pandas_decimal-0.0.1.dist-info/METADATA
pandas_decimal-0.0.1.dist-info/WHEEL
pandas_decimal-0.0.1.dist-info/top_level.txt
pandas_decimal-0.0.1.dist-info/RECORD
