Metadata-Version: 2.1
Name: pandas-decimal
Version: 0.0.1
Summary: icy
Author-email: Martin Durant <mdurant@anaconda.com>
Maintainer-email: Martin Durant <mdurant@anaconda.com>
Classifier: Development Status :: 3 - Alpha
Classifier: License :: OSI Approved :: BSD License
Classifier: Programming Language :: Python :: 3
Classifier: Programming Language :: Python :: 3 :: Only
Classifier: Programming Language :: Python :: 3.8
Classifier: Programming Language :: Python :: 3.9
Classifier: Programming Language :: Python :: 3.10
Classifier: Topic :: Scientific/Engineering
Requires-Python: >=3.8
License-File: LICENSE
Requires-Dist: pandas
